facety/__init__.py
facety-0.0.3.dist-info/METADATA
facety-0.0.3.dist-info/WHEEL
facety-0.0.3.dist-info/top_level.txt
facety-0.0.3.dist-info/RECORD
